LICENSE
README.md
pyproject.toml
setup.py
deps/requirements.in
src/python_import/__init__.py
src/python_import/_version.py
src/python_import/ts_utils.py
src/python_import/utils.py
src/python_import.egg-info/PKG-INFO
src/python_import.egg-info/SOURCES.txt
src/python_import.egg-info/dependency_links.txt
src/python_import.egg-info/entry_points.txt
src/python_import.egg-info/requires.txt
src/python_import.egg-info/top_level.txt
src/python_import/cli/__init__.py
src/python_import/cli/main.py
tests/test_one_file.py