Metadata-Version: 2.1
Name: python-import
Version: 0.1.0
Summary: Neovim plugin for python autoimports.
Author: Kiyoon Kim
License: MIT License
Project-URL: Homepage, https://github.com/kiyoon/python-import.nvim
Keywords: neovim,nvim,nvim-plugin,python,python-import
Classifier: Programming Language :: Python
Classifier: Programming Language :: Python :: 3
Classifier: Programming Language :: Python :: 3.9
Classifier: Programming Language :: Python :: 3.10
Classifier: Programming Language :: Python :: 3.11
Classifier: Programming Language :: Python :: 3.12
Requires-Python: <3.13,>=3.9
License-File: LICENSE
Requires-Dist: typer>=0.12.4
Requires-Dist: tree-sitter>=0.23.0
Requires-Dist: tree-sitter-python>=0.23.0
